canvas_download/__init__.py
canvas_download/canvas_download.py
canvas_download-1.1.6.dist-info/METADATA
canvas_download-1.1.6.dist-info/WHEEL
canvas_download-1.1.6.dist-info/entry_points.txt
canvas_download-1.1.6.dist-info/licenses/LICENSE.txt
canvas_download-1.1.6.dist-info/RECORD
