Metadata-Version: 2.4
Name: canvas-download
Version: 1.1.6
Summary: Downloads Canvas modules/files into a local directory.
Project-URL: Homepage, https://github.com/suncloudsmoon/canvas-download
Project-URL: Issues, https://github.com/suncloudsmoon/canvas-download/issues
Author-email: suncloudsmoon <farsaturn@outlook.com>
License-Expression: MIT
License-File: LICENSE.txt
Keywords: canvas,canvas-grab,download,downloader,offline,sync,utility
Classifier: Development Status :: 5 - Production/Stable
Classifier: Environment :: Console
Classifier: Intended Audience :: Education
Classifier: License :: OSI Approved :: MIT License
Classifier: Operating System :: OS Independent
Classifier: Programming Language :: Python :: 3
Classifier: Programming Language :: Python :: 3.10
Classifier: Programming Language :: Python :: 3.11
Classifier: Programming Language :: Python :: 3.12
Classifier: Programming Language :: Python :: 3.13
Classifier: Programming Language :: Python :: 3.14
Classifier: Topic :: Utilities
Requires-Python: >=3.10
Requires-Dist: canvasapi>=3.3.0
Requires-Dist: pywin32; platform_system == 'Windows'
Requires-Dist: tqdm>=4.67.1
